[
  {
    "id":   1,
    "name": "河北",
    "pid":  0
  },
  {
    "id":   2,
    "name": "山西",
    "pid":  0
  },
  {
    "id":   3,
    "name": "石家庄",
    "pid":  1
  },
  {
    "id":   4,
    "name": "保定",
    "pid":  1
  },
  {
    "id":   5,
    "name": "太原",
    "pid":  2
  },
  {
    "id":   6,
    "name": "大同",
    "pid":  2
  },
  {
    "id":   7,
    "name": "长安区",
    "pid":  3
  },
  {
    "id":   8,
    "name": "桥西区",
    "pid":  3
  },
  {
    "id":   9,
    "name": "小店区",
    "pid":  5
  },
  {
    "id":   10,
    "name": "迎泽区",
    "pid":  5
  }
]